pytest_historic_hook/__init__.py
pytest_historic_hook/plugin.py
pytest_historic_hook-0.1.2.dist-info/LICENSE
pytest_historic_hook-0.1.2.dist-info/METADATA
pytest_historic_hook-0.1.2.dist-info/WHEEL
pytest_historic_hook-0.1.2.dist-info/entry_points.txt
pytest_historic_hook-0.1.2.dist-info/top_level.txt
pytest_historic_hook-0.1.2.dist-info/zip-safe
pytest_historic_hook-0.1.2.dist-info/RECORD
